.gitignore
LICENSE
Makefile
pyproject.toml
scene.yaml
.github/dependabot.yml
.github/workflows/auto-merge.yml
.github/workflows/dependency-review.yml
.github/workflows/lint.yml
.github/workflows/release.yml
fabler/__init__.py
fabler/__main__.py
fabler/config.py
fabler/model.py
fabler/server.py
fabler/pipelines/__init__.py
fabler/pipelines/animator.py
fabler/pipelines/painter.py
fabler/pipelines/speaker.py
fabler/pipelines/writer.py
fabler/routes/.gitkeep
fabler/static/www/index.html
fabler/static/www/assets/css/primer.css
fabler/static/www/assets/css/style.css
fabler/static/www/assets/js/main.js
fabler/static/www/assets/templates/.gitkeep
fabler/utils/__init__.py
fabler/utils/common.py
fabler-0.0.6.dist-info/METADATA
fabler-0.0.6.dist-info/WHEEL
fabler-0.0.6.dist-info/entry_points.txt
fabler-0.0.6.dist-info/licenses/LICENSE
fabler-0.0.6.dist-info/RECORD
