Metadata-Version: 2.1
Name: fabler
Version: 0.0.6
Summary: Multimodal AI Story Teller, built with Stable Diffusion, GPT, and neural text-to-speech.
Project-URL: GitHub, https://github.com/christopherwoodall/fabler
Author-email: Christopher Woodall <woodall.christopher@gmail.com>
License-Expression: MIT
License-File: LICENSE
Keywords: GPT,TTS,language-model,multimodal AI,neural text-to-speech,stable diffusion,transformer
Classifier: Development Status :: 1 - Planning
Classifier: Environment :: Console
Classifier: Environment :: GPU
Classifier: Environment :: Web Environment
Classifier: Framework :: Flask
Classifier: Framework :: Hatch
Classifier: Intended Audience :: Developers
Classifier: Intended Audience :: End Users/Desktop
Classifier: Intended Audience :: Science/Research
Classifier: License :: OSI Approved :: MIT License
Classifier: Natural Language :: English
Classifier: Operating System :: OS Independent
Classifier: Programming Language :: Python
Classifier: Programming Language :: Python :: 3.8
Classifier: Programming Language :: Python :: 3.9
Classifier: Programming Language :: Python :: 3.10
Classifier: Topic :: Scientific/Engineering :: Artificial Intelligence
Requires-Python: >=3.8
Requires-Dist: accelerate[test-trackers]
Requires-Dist: diffusers
Requires-Dist: flask
Requires-Dist: nltk
Requires-Dist: pyyaml
Requires-Dist: tensorboard
Requires-Dist: transformers
Requires-Dist: tts
Provides-Extra: developer
Requires-Dist: black; extra == 'developer'
Requires-Dist: flake8; extra == 'developer'
Requires-Dist: hatch; extra == 'developer'
Requires-Dist: isort; extra == 'developer'
Requires-Dist: mypy; extra == 'developer'
Requires-Dist: pre-commit; extra == 'developer'
Requires-Dist: pydantic; extra == 'developer'
Requires-Dist: types-pyyaml; extra == 'developer'
Provides-Extra: staging
Requires-Dist: sentence-transformers>=2.2.0; extra == 'staging'
